django_tag_me-2026.1.7.1.dist-info/licenses/LICENSE
tag_me/__init__.py
tag_me/admin.py
tag_me/apps.py
tag_me/assets.py
tag_me/registry.py
tag_me/urls.py
tag_me/widgets.py
tag_me/forms/__init__.py
tag_me/forms/fields.py
tag_me/forms/forms.py
tag_me/forms/mixins.py
tag_me/management/commands/createsuperuser_for_testing.py
tag_me/management/commands/populate_tags.py
tag_me/migrations/0001_initial.py
tag_me/migrations/0002_systemtag_search_tags_usertag_search_tags_and_more.py
tag_me/migrations/0003_systemtag_comment_systemtag_field_name_and_more.py
tag_me/migrations/0004_fk_lookup_refactor.py
tag_me/migrations/0005_remove_taggedfieldmodel_unique_tagged_field_model_and_more.py
tag_me/migrations/__init__.py
tag_me/models/__init__.py
tag_me/models/fields.py
tag_me/models/models.py
tag_me/static/tag_me/dist/manifest.json
tag_me/static/tag_me/dist/css/tag-me.Ir3adWu5.css
tag_me/static/tag_me/dist/js/tag-me.D7ykXiGd.js
tag_me/templates/base.html
tag_me/templates/tag_me/tag_me_bottom_sheet.html
tag_me/templates/tag_me/tag_me_mobile_footer.html
tag_me/templates/tag_me/tag_me_select.html
tag_me/templates/tag_me/tag_me_select_search_bar_desktop.html
tag_me/templates/tag_me/tag_me_select_search_bar_mobile.html
tag_me/templates/tag_me/archived/tag_me_select.html
tag_me/templates/tag_me/archived/tag_me_select_search_bar_menu.html
tag_me/templates/tag_me/mgmt/edit_tagged_fields.html
tag_me/templates/tag_me/mgmt/list_user_tag.html
tag_me/templates/tag_me/mgmt/management.html
tag_me/templates/tag_me/mgmt/sync_tagged_field_list.html
tag_me/templates/tag_me/mgmt/tagged_field_list.html
tag_me/templates/tag_me/no_prefix/tag_me_bottom_sheet.html
tag_me/templates/tag_me/no_prefix/tag_me_mobile_footer.html
tag_me/templates/tag_me/no_prefix/tag_me_select.html
tag_me/templates/tag_me/no_prefix/tag_me_select_search_bar_desktop.html
tag_me/templates/tag_me/no_prefix/tag_me_select_search_bar_mobile.html
tag_me/templates/tag_me/prefix/tag_me_bottom_sheet.html
tag_me/templates/tag_me/prefix/tag_me_mobile_footer.html
django_tag_me-2026.1.7.1.dist-info/METADATA
django_tag_me-2026.1.7.1.dist-info/WHEEL
django_tag_me-2026.1.7.1.dist-info/top_level.txt
django_tag_me-2026.1.7.1.dist-info/RECORD
