Metadata-Version: 2.4
Name: django-tag-me
Version: 2026.1.7.1
Summary: A simple approach to Django tagging
Author-email: Mark Sevelj <mark.sevelj@dunwright.com.au>
Maintainer-email: Mark Sevelj <mark.sevelj@dunwright.com.au>
License: BSD-3-Clause
Project-URL: Repository, https://github.com/imAsparky/django-tag-me
Project-URL: Documentation, https://django-tag-me.readthedocs.io
Project-URL: Tracker, https://github.com/imAsparky/django-tag-me/issues
Project-URL: Changelog, https://github.com/imAsparky/django-tag-me/blob/main/CHANGELOG.md
Keywords: Django Tag Me,Django,django,django tagging,Django tags,Django field tags
Classifier: Development Status :: 4 - Beta
Classifier: Environment :: Web Environment
Classifier: Framework :: Django
Classifier: Framework :: Django :: 4.0
Classifier: Framework :: Django :: 4.1
Classifier: Framework :: Django :: 4.2
Classifier: Framework :: Django :: 5.0
Classifier: Framework :: Django :: 5.1
Classifier: Framework :: Django :: 5.2
Classifier: Intended Audience :: Developers
Classifier: License :: OSI Approved :: BSD License
Classifier: Operating System :: OS Independent
Classifier: Programming Language :: Python
Classifier: Programming Language :: Python :: 3.10
Classifier: Programming Language :: Python :: 3.11
Classifier: Programming Language :: Python :: 3.12
Classifier: Programming Language :: Python :: 3.13
Requires-Python: >=3.10
License-File: LICENSE
Requires-Dist: Django>=4.0
Requires-Dist: structlog
Provides-Extra: dev
Requires-Dist: django-extensions; extra == "dev"
Requires-Dist: hypothesis; extra == "dev"
Requires-Dist: pyright; extra == "dev"
Requires-Dist: pytest; extra == "dev"
Requires-Dist: pytest-django; extra == "dev"
Requires-Dist: pytest-cov; extra == "dev"
Requires-Dist: tox; extra == "dev"
Dynamic: license-file
